wagtail_events/__init__.py
wagtail_events/abstract_models.py
wagtail_events/date_filters.py
wagtail_events/managers.py
wagtail_events/models.py
wagtail_events/utils.py
wagtail_events/views.py
wagtail_events/migrations/0001_initial.py
wagtail_events/migrations/0002_rename_events_models.py
wagtail_events/migrations/__init__.py
wagtail_events/templatetags/__init__.py
wagtail_events/templatetags/wagtail_events_tags.py
wagtail_events-0.0.1.dist-info/LICENSE
wagtail_events-0.0.1.dist-info/METADATA
wagtail_events-0.0.1.dist-info/WHEEL
wagtail_events-0.0.1.dist-info/top_level.txt
wagtail_events-0.0.1.dist-info/RECORD
