Metadata-Version: 2.1
Name: wagtail-events
Version: 0.0.1
Summary: Event features for Wagtail
Home-page: https://github.com/thclark/wagtail_events
Author: thclark
Author-email: UNKNOWN
License: MIT License
Requires-Dist: wagtail (>=2.3)
Requires-Dist: isoweek (==1.3.3)
Requires-Dist: python-dateutil (==2.8.0)
